ajax_helpers/__init__.py
ajax_helpers/apps.py
ajax_helpers/html_include.py
ajax_helpers/includes.py
ajax_helpers/mixins.py
ajax_helpers/screen_capture.py
ajax_helpers/utils.py
ajax_helpers/static/ajax_helpers/ajax_helpers.css
ajax_helpers/static/ajax_helpers/ajax_helpers.js
ajax_helpers/static/ajax_helpers/ajax_helpers_legacy.js
ajax_helpers/static/ajax_helpers/screen_capture.js
ajax_helpers/static/ajax_helpers/css/bootstrap.min.css
ajax_helpers/static/ajax_helpers/css/bootstrap.min.css.map
ajax_helpers/static/ajax_helpers/fontawesome/css/all.css
ajax_helpers/static/ajax_helpers/fontawesome/webfonts/fa-brands-400.eot
ajax_helpers/static/ajax_helpers/fontawesome/webfonts/fa-brands-400.svg
ajax_helpers/static/ajax_helpers/fontawesome/webfonts/fa-brands-400.ttf
ajax_helpers/static/ajax_helpers/fontawesome/webfonts/fa-brands-400.woff
ajax_helpers/static/ajax_helpers/fontawesome/webfonts/fa-brands-400.woff2
ajax_helpers/static/ajax_helpers/fontawesome/webfonts/fa-regular-400.eot
ajax_helpers/static/ajax_helpers/fontawesome/webfonts/fa-regular-400.svg
ajax_helpers/static/ajax_helpers/fontawesome/webfonts/fa-regular-400.ttf
ajax_helpers/static/ajax_helpers/fontawesome/webfonts/fa-regular-400.woff
ajax_helpers/static/ajax_helpers/fontawesome/webfonts/fa-regular-400.woff2
ajax_helpers/static/ajax_helpers/fontawesome/webfonts/fa-solid-900.eot
ajax_helpers/static/ajax_helpers/fontawesome/webfonts/fa-solid-900.svg
ajax_helpers/static/ajax_helpers/fontawesome/webfonts/fa-solid-900.ttf
ajax_helpers/static/ajax_helpers/fontawesome/webfonts/fa-solid-900.woff
ajax_helpers/static/ajax_helpers/fontawesome/webfonts/fa-solid-900.woff2
ajax_helpers/static/ajax_helpers/js/bootstrap.min.js
ajax_helpers/static/ajax_helpers/js/bootstrap.min.js.map
ajax_helpers/static/ajax_helpers/js/code.jquery.com_jquery-3.7.1.min.js
ajax_helpers/static/ajax_helpers/js/jquery-3.7.0.min.js
ajax_helpers/static/ajax_helpers/js/jquery.min.js
ajax_helpers/static/ajax_helpers/js/jquery.min.old.js
django_ajax_helpers-0.0.22.dist-info/LICENSE
django_ajax_helpers-0.0.22.dist-info/METADATA
django_ajax_helpers-0.0.22.dist-info/WHEEL
django_ajax_helpers-0.0.22.dist-info/top_level.txt
django_ajax_helpers-0.0.22.dist-info/RECORD
