Metadata-Version: 2.1
Name: django-ajax-helpers
Version: 0.0.22
Summary: Django app to assist with posting Ajax and receiving commands from django
Home-page: https://github.com/jonesim/ajax-helpers
Author: Ian Jones
License: UNKNOWN
Platform: UNKNOWN
Classifier: Programming Language :: Python :: 3
Classifier: License :: OSI Approved :: MIT License
Classifier: Operating System :: OS Independent
Requires-Python: >=3.6
